dataspyv4/__init__.py
dataspyv4/categoryfucntion.py
dataspyv4/centraltendency.py
dataspyv4/charts.py
dataspyv4/dataspyv4.py
dataspyv4/utils.py
dataspyv4-0.4.dist-info/METADATA
dataspyv4-0.4.dist-info/WHEEL
dataspyv4-0.4.dist-info/top_level.txt
dataspyv4-0.4.dist-info/RECORD
